.gitignore
MANIFEST.in
Makefile
Pipfile
README.md
pipfile_parse.py
requirements-dev.txt
requirements.txt
settings.ini
setup.py
lib_example_12345/__init__.py
lib_example_12345/_nbdev.py
lib_example_12345/module.py
lib_example_12345.egg-info/PKG-INFO
lib_example_12345.egg-info/SOURCES.txt
lib_example_12345.egg-info/dependency_links.txt
lib_example_12345.egg-info/requires.txt
lib_example_12345.egg-info/top_level.txt
nbs/00-module.ipynb