Metadata-Version: 2.1
Name: lib-example-12345
Version: 0.0.3
Summary: A description of your project
License: UNKNOWN
Platform: UNKNOWN
